mostfiles/__init__.py
mostfiles-0.0.3.dist-info/METADATA
mostfiles-0.0.3.dist-info/WHEEL
mostfiles-0.0.3.dist-info/entry_points.txt
mostfiles-0.0.3.dist-info/licenses/LICENSE
mostfiles-0.0.3.dist-info/RECORD
