Metadata-Version: 2.3
Name: mostfiles
Version: 0.0.3
Summary: Find directories which contains most files
Project-URL: Homepage, https://github.com/yaroslaff/mostfiles
Project-URL: Issues, https://github.com/yaroslaff/mostfiles/issues
Author-email: Yaroslav Polyakov <yaroslaff@gmail.com>
License-File: LICENSE
Classifier: License :: OSI Approved :: MIT License
Classifier: Operating System :: OS Independent
Classifier: Programming Language :: Python :: 3
Requires-Python: >=3.6
